qnetvo/__init__.py
qnetvo/ansatz_library.py
qnetvo/gradient_descent.py
qnetvo/information.py
qnetvo/lazy_dask_import.py
qnetvo/lazy_tensorflow_import.py
qnetvo/network_ansatz.py
qnetvo/network_nodes.py
qnetvo/postprocessing.py
qnetvo/qnodes.py
qnetvo/utilities.py
qnetvo/version.py
qnetvo/cost/I_3322_bell_inequality.py
qnetvo/cost/__init__.py
qnetvo/cost/chsh_inequality.py
qnetvo/cost/linear_inequalities.py
qnetvo/cost/magic_squares_game.py
qnetvo/cost/mermin_klyshko_inequality.py
qnetvo/cost/mutual_info.py
qnetvo/cost/nlocal_chain_bell_inequality.py
qnetvo/cost/nlocal_star_bell_inequality.py
qNetVO-0.4.4.dist-info/LICENSE
qNetVO-0.4.4.dist-info/METADATA
qNetVO-0.4.4.dist-info/NOTICE.txt
qNetVO-0.4.4.dist-info/WHEEL
qNetVO-0.4.4.dist-info/top_level.txt
qNetVO-0.4.4.dist-info/RECORD
