Metadata-Version: 2.1
Name: qNetVO
Version: 0.4.4
Summary: The Quantum Network Variational Optimizer
Home-page: https://github.com/ChitambarLab/qNetVO
Author: Brian Doolittle and Tom Bromley
Author-email: brian.d.doolittle@gmail.com
Project-URL: Bug Tracker, https://github.com/ChitambarLab/qNetVO
Classifier: Programming Language :: Python :: 3
Classifier: License :: OSI Approved :: Apache Software License
Classifier: Operating System :: OS Independent
Requires-Python: >=3.9
License-File: LICENSE
License-File: NOTICE.txt
Requires-Dist: pennylane ==0.37
